dqcsim_qx-0.0.5.data/data/bin/dqcsbeqx
dqcsim_qx-0.0.5.data/data/bin/dqcsbeqx.libs/libgomp-f7e03b3e.so.1.0.0
dqcsim_qx-0.0.5.data/purelib/dqcsim_qx/test.py
dqcsim_qx-0.0.5.data/purelib/dqcsim_qx/__init__.py
dqcsim_qx-0.0.5.dist-info/METADATA
dqcsim_qx-0.0.5.dist-info/RECORD
dqcsim_qx-0.0.5.dist-info/WHEEL
dqcsim_qx-0.0.5.dist-info/top_level.txt
