Metadata-Version: 2.1
Name: dqcsim-qx
Version: 0.0.5
Summary: A DQCsim backend for the QX simulator
Home-page: https://github.com/QE-Lab/dqcsim-qx
Author: Quantum Computer Architectures, Quantum & Computer Engineering, QuTech, Delft University of Technology
Author-email: 
License: Apache-2.0
Project-URL: Source Code, https://github.com/QE-Lab/dqcsim-qx
Platform: UNKNOWN
Classifier: License :: OSI Approved :: Apache Software License
Classifier: Operating System :: POSIX :: Linux
Classifier: Programming Language :: C
Classifier: Programming Language :: C++
Classifier: Topic :: Scientific/Engineering
Requires-Dist: dqcsim
